perf_sentinel/__init__.py
perf_sentinel/audit/__init__.py
perf_sentinel/audit/scheduler.py
perf_sentinel/audit/trend_analyzer.py
perf_sentinel/ci/__init__.py
perf_sentinel/ci/cli.py
perf_sentinel/ci/github_actions.py
perf_sentinel/ci/gitlab_ci.py
perf_sentinel/decorators/__init__.py
perf_sentinel/decorators/async_utils.py
perf_sentinel/decorators/timing.py
perf_sentinel/reporter/__init__.py
perf_sentinel/reporter/aioflame_integration.py
perf_sentinel/reporter/pyspy_integration.py
perf_sentinel/reporter/report_builder.py
perf_sentinel/utils/__init__.py
perf_sentinel/utils/env_detect.py
perf_sentinel/utils/json_logger.py
perf_sentinel-0.1.2.dist-info/METADATA
perf_sentinel-0.1.2.dist-info/WHEEL
perf_sentinel-0.1.2.dist-info/entry_points.txt
perf_sentinel-0.1.2.dist-info/top_level.txt
perf_sentinel-0.1.2.dist-info/RECORD
